xsentinels/__init__.py
xsentinels/default.py
xsentinels/null.py
xsentinels/py.typed
xsentinels/sentinel.py
xsentinels/singleton.py
xsentinels/unwrap.py
xsentinels-1.3.1.dist-info/LICENSE
xsentinels-1.3.1.dist-info/METADATA
xsentinels-1.3.1.dist-info/WHEEL
xsentinels-1.3.1.dist-info/RECORD
