Metadata-Version: 2.3
Name: xsentinels
Version: 1.3.1
Summary: Sentinels for Defaults, Null and for creating sentinels/singletons.
Keywords: singleton,type,guards,sentinels,sentinel,default,null
Author: Josh Orr
Author-email: josh@orr.blue
Requires-Python: >=3.10,<4.0
Classifier: License :: OSI Approved :: The Unlicense (Unlicense)
Classifier: Programming Language :: Python :: 3
Classifier: Programming Language :: Python :: 3.10
Classifier: Programming Language :: Python :: 3.11
Classifier: Programming Language :: Python :: 3.12
Classifier: Programming Language :: Python :: 3.13
Classifier: Topic :: Software Development :: Libraries :: Python Modules
Requires-Dist: typing-inspect (>=0,<1)
Project-URL: Repository, https://github.com/xyngular/py-xsentinels
